[{"pk":1,"model":"artists.artist","fields":{"artist_name":"RandyRMM","artist_url":"https://pixabay.com/users/randyrmm-11051907/","created":"2022-04-19 13:36:51"}},{"pk":2,"model":"artists.artist","fields":{"artist_name":"intographics","artist_url":"https://pixabay.com/users/intographics-2633886/","created":"2022-04-19 13:36:51"}},{"pk":3,"model":"artists.artist","fields":{"artist_name":"ivanovgood","artist_url":"https://pixabay.com/users/ivanovgood-1982503/","created":"2022-04-19 13:36:51"}},{"pk":4,"model":"artists.artist","fields":{"artist_name":"PublicDomainPictures","artist_url":"https://pixabay.com/users/publicdomainpictures-14/","created":"2022-04-19 13:36:51"}},{"pk":5,"model":"artists.artist","fields":{"artist_name":"CDD20","artist_url":"https://pixabay.com/users/cdd20-1193381/","created":"2022-04-19 13:36:51"}},{"pk":6,"model":"artists.artist","fields":{"artist_name":"ractapopulous","artist_url":"https://pixabay.com/users/ractapopulous-24766/","created":"2022-04-19 13:36:51"}},{"pk":7,"model":"artists.artist","fields":{"artist_name":"ninocare","artist_url":"https://pixabay.com/users/ninocare-3266770/","created":"2022-04-19 13:36:51"}},{"pk":8,"model":"artists.artist","fields":{"artist_name":"aalmeidah","artist_url":"https://pixabay.com/users/aalmeidah-4277022/","created":"2022-04-19 13:36:51"}},{"pk":9,"model":"artists.artist","fields":{"artist_name":"Pexels","artist_url":"https://pixabay.com/users/pexels-2286921/","created":"2022-04-19 13:36:51"}},{"pk":10,"model":"artists.artist","fields":{"artist_name":"HitaJast","artist_url":"https://pixabay.com/users/hitajast-23045237/","created":"2022-04-19 13:36:51"}},{"pk":11,"model":"artists.artist","fields":{"artist_name":"Ylanite","artist_url":"https://pixabay.com/users/ylanite-2218222/","created":"2022-04-19 13:36:51"}},{"pk":12,"model":"artists.artist","fields":{"artist_name":"Shirley810","artist_url":"https://pixabay.com/users/shirley810-9355/","created":"2022-04-19 13:36:51"}},{"pk":13,"model":"artists.artist","fields":{"artist_name":"lavnatalia","artist_url":"https://pixabay.com/users/lavnatalia-5858294/","created":"2022-04-19 13:36:51"}},{"pk":14,"model":"artists.artist","fields":{"artist_name":"bodobe","artist_url":"https://pixabay.com/users/bodobe-1222375/","created":"2022-04-19 13:36:51"}},{"pk":15,"model":"artists.artist","fields":{"artist_name":"geralt","artist_url":"https://pixabay.com/users/geralt-9301/","created":"2022-04-19 13:36:51"}},{"pk":16,"model":"artists.artist","fields":{"artist_name":"weinstock","artist_url":"https://pixabay.com/users/weinstock-25534/","created":"2022-04-19 13:36:51"}},{"pk":17,"model":"artists.artist","fields":{"artist_name":"SarahRichterArt","artist_url":"https://pixabay.com/users/sarahrichterart-1546275/","created":"2022-04-19 13:36:51"}},{"pk":18,"model":"artists.artist","fields":{"artist_name":"pencilparker","artist_url":"https://pixabay.com/users/pencilparker-7519217/","created":"2022-04-19 13:36:51"}},{"pk":19,"model":"artists.artist","fields":{"artist_name":"merlinlightpainting","artist_url":"https://pixabay.com/users/merlinlightpainting-19833603/","created":"2022-04-19 13:36:51"}},{"pk":20,"model":"artists.artist","fields":{"artist_name":"josch13","artist_url":"https://pixabay.com/users/josch13-48777/","created":"2022-04-19 13:36:51"}},{"pk":21,"model":"artists.artist","fields":{"artist_name":"saydung89","artist_url":"https://pixabay.com/users/saydung89-18713596/","created":"2022-04-19 13:36:51"}},{"pk":22,"model":"artists.artist","fields":{"artist_name":"BiancaVanDijk","artist_url":"https://pixabay.com/users/biancavandijk-9606149/","created":"2022-04-19 13:36:51"}},{"pk":23,"model":"artists.artist","fields":{"artist_name":"cromaconceptovisual","artist_url":"https://pixabay.com/users/cromaconceptovisual-4595909/","created":"2022-04-19 13:36:51"}},{"pk":24,"model":"artists.artist","fields":{"artist_name":"Nika_Akin","artist_url":"https://pixabay.com/users/nika_akin-13521770/","created":"2022-04-19 13:36:51"}},{"pk":25,"model":"artists.artist","fields":{"artist_name":"ZERIG","artist_url":"https://pixabay.com/users/zerig-934572/","created":"2022-04-19 13:36:51"}},{"pk":26,"model":"artists.artist","fields":{"artist_name":"ninikvaratskhelia_","artist_url":"https://pixabay.com/users/ninikvaratskhelia_-15913392/","created":"2022-04-19 13:36:51"}},{"pk":27,"model":"artists.artist","fields":{"artist_name":"digihanger","artist_url":"https://pixabay.com/users/digihanger-28124/","created":"2022-04-19 13:36:51"}},{"pk":28,"model":"artists.artist","fields":{"artist_name":"No-longer-here","artist_url":"https://pixabay.com/users/no-longer-here-19203/","created":"2022-04-19 13:36:51"}},{"pk":29,"model":"artists.artist","fields":{"artist_name":"regencygirl123","artist_url":"https://pixabay.com/users/regencygirl123-5268654/","created":"2022-04-19 13:36:51"}},{"pk":30,"model":"artists.artist","fields":{"artist_name":"GDJ","artist_url":"https://pixabay.com/users/gdj-1086657/","created":"2022-04-19 13:36:51"}},{"pk":31,"model":"artists.artist","fields":{"artist_name":"652234","artist_url":"https://pixabay.com/users/652234-652234/","created":"2022-04-19 13:36:51"}},{"pk":32,"model":"artists.artist","fields":{"artist_name":"Leohoho","artist_url":"https://pixabay.com/users/leohoho-16235524/","created":"2022-04-19 13:36:51"}},{"pk":33,"model":"artists.artist","fields":{"artist_name":"0fjd125gk87","artist_url":"https://pixabay.com/users/0fjd125gk87-51581/","created":"2022-04-19 13:36:51"}},{"pk":34,"model":"artists.artist","fields":{"artist_name":"Yuri_B","artist_url":"https://pixabay.com/users/yuri_b-2216431/","created":"2022-04-19 13:36:51"}},{"pk":35,"model":"artists.artist","fields":{"artist_name":"virin000","artist_url":"https://pixabay.com/users/virin000-4559233/","created":"2022-04-19 13:36:51"}},{"pk":36,"model":"artists.artist","fields":{"artist_name":"Engin_Akyurt","artist_url":"https://pixabay.com/users/engin_akyurt-3656355/","created":"2022-04-19 13:36:51"}},{"pk":37,"model":"artists.artist","fields":{"artist_name":"naobim","artist_url":"https://pixabay.com/users/naobim-1099306/","created":"2022-04-19 13:36:51"}},{"pk":38,"model":"artists.artist","fields":{"artist_name":"eluela31","artist_url":"https://pixabay.com/users/eluela31-4894494/","created":"2022-04-19 13:36:51"}},{"pk":39,"model":"artists.artist","fields":{"artist_name":"Skitterphoto","artist_url":"https://pixabay.com/users/skitterphoto-324082/","created":"2022-04-19 13:36:51"}},{"pk":40,"model":"artists.artist","fields":{"artist_name":"1681551","artist_url":"https://pixabay.com/users/1681551-1681551/","created":"2022-04-19 13:36:51"}},{"pk":41,"model":"artists.artist","fields":{"artist_name":"Darkmoon_Art","artist_url":"https://pixabay.com/users/darkmoon_art-1664300/","created":"2022-04-19 13:36:51"}},{"pk":42,"model":"artists.artist","fields":{"artist_name":"Wangphan","artist_url":"https://pixabay.com/users/wangphan-23172418/","created":"2022-04-19 13:36:51"}},{"pk":43,"model":"artists.artist","fields":{"artist_name":"stux","artist_url":"https://pixabay.com/users/stux-12364/","created":"2022-04-19 13:36:51"}},{"pk":44,"model":"artists.artist","fields":{"artist_name":"Myriams-Fotos","artist_url":"https://pixabay.com/users/myriams-fotos-1627417/","created":"2022-04-19 13:36:51"}},{"pk":45,"model":"artists.artist","fields":{"artist_name":"KELLEPICS","artist_url":"https://pixabay.com/users/kellepics-4893063/","created":"2022-04-19 13:36:51"}},{"pk":46,"model":"artists.artist","fields":{"artist_name":"WikiImages","artist_url":"https://pixabay.com/users/wikiimages-1897/","created":"2022-04-19 13:36:51"}},{"pk":47,"model":"artists.artist","fields":{"artist_name":"Deflyne","artist_url":"https://pixabay.com/users/deflyne-7853109/","created":"2022-04-19 13:36:51"}},{"pk":48,"model":"artists.artist","fields":{"artist_name":"mohamed_hassan","artist_url":"https://pixabay.com/users/mohamed_hassan-5229782/","created":"2022-04-19 13:36:51"}},{"pk":49,"model":"artists.artist","fields":{"artist_name":"Studio-Dee","artist_url":"https://pixabay.com/users/studio-dee-6078268/","created":"2022-04-19 13:36:51"}},{"pk":50,"model":"artists.artist","fields":{"artist_name":"StockSnap","artist_url":"https://pixabay.com/users/stocksnap-894430/","created":"2022-04-19 13:36:51"}},{"pk":51,"model":"artists.artist","fields":{"artist_name":"Bingodesigns","artist_url":"https://pixabay.com/users/bingodesigns-213864/","created":"2022-04-19 13:36:51"}},{"pk":52,"model":"artists.artist","fields":{"artist_name":"GLady","artist_url":"https://pixabay.com/users/glady-768/","created":"2022-04-19 13:36:51"}},{"pk":53,"model":"artists.artist","fields":{"artist_name":"sanctumdigital","artist_url":"https://pixabay.com/users/sanctumdigital-10596213/","created":"2022-04-19 13:36:51"}},{"pk":54,"model":"artists.artist","fields":{"artist_name":"OpenClipart-Vectors","artist_url":"https://pixabay.com/users/openclipart-vectors-30363/","created":"2022-04-19 13:36:51"}},{"pk":55,"model":"artists.artist","fields":{"artist_name":"Manuchi","artist_url":"https://pixabay.com/users/manuchi-1728328/","created":"2022-04-19 13:36:51"}},{"pk":56,"model":"artists.artist","fields":{"artist_name":"wastmpds","artist_url":"https://pixabay.com/users/wastmpds-19795624/","created":"2022-04-19 13:36:51"}},{"pk":57,"model":"artists.artist","fields":{"artist_name":"_Namfon_","artist_url":"https://pixabay.com/users/_namfon_-16559457/","created":"2022-04-19 13:36:51"}},{"pk":58,"model":"artists.artist","fields":{"artist_name":"Leolo212","artist_url":"https://pixabay.com/users/leolo212-15013188/","created":"2022-04-19 13:36:51"}},{"pk":59,"model":"artists.artist","fields":{"artist_name":"tangjiao990","artist_url":"https://pixabay.com/users/tangjiao990-1595606/","created":"2022-04-19 13:36:51"}},{"pk":60,"model":"artists.artist","fields":{"artist_name":"8926","artist_url":"https://pixabay.com/users/8926-8926/","created":"2022-04-19 13:36:51"}}]